[
	{
		"id": "Exabeam Incident",
		"version": 1,
		"cacheVersn": 0,
		"modified": "2022-11-24T10:57:12.481538+02:00",
		"packID": "",
		"packName": "",
		"itemVersion": "",
		"fromServerVersion": "",
		"toServerVersion": "",
		"definitionId": "",
		"vcShouldIgnore": false,
		"vcShouldKeepItemLegacyProdMachine": false,
		"commitMessage": "",
		"shouldCommit": false,
		"locked": false,
		"name": "Exabeam Incident",
		"prevName": "Exabeam Incident",
		"color": "#F8E7A5",
		"hours": 0,
		"days": 0,
		"weeks": 0,
		"hoursR": 0,
		"daysR": 0,
		"weeksR": 0,
		"system": false,
		"readonly": false,
		"default": false,
		"autorun": false,
		"preProcessingScript": "",
		"closureScript": "",
		"disabled": false,
		"reputationCalc": 0,
		"onChangeRepAlg": 0,
		"layout": "",
		"detached": false,
		"extractSettings": {
			"mode": "Specific",
			"fieldCliNameToExtractSettings": {}
		}
	}
]